hsr/__init__.py
hsr/fingerprint.py
hsr/hsr_cli.py
hsr/pca_transform.py
hsr/pre_processing.py
hsr/similarity.py
hsr/utils.py
hsr-0.1.26.dist-info/licenses/LICENSE
hsr-0.1.26.dist-info/METADATA
hsr-0.1.26.dist-info/WHEEL
hsr-0.1.26.dist-info/entry_points.txt
hsr-0.1.26.dist-info/top_level.txt
hsr-0.1.26.dist-info/RECORD
