Metadata-Version: 2.4
Name: hsr
Version: 0.1.26
Summary: Hypershape recognition (HSR): a general framework for moment-based similarity measures
Author: Marcello Costamagna
License: AGPL-3.0
License-File: LICENSE
Requires-Dist: numpy
Requires-Dist: scipy
Requires-Dist: rdkit
Dynamic: author
Dynamic: description
Dynamic: description-content-type
Dynamic: license
Dynamic: license-file
Dynamic: requires-dist
Dynamic: summary
